README.md
setup.py
agensgraph/__init__.py
agensgraph/connect.py
agensgraph.egg-info/PKG-INFO
agensgraph.egg-info/SOURCES.txt
agensgraph.egg-info/dependency_links.txt
agensgraph.egg-info/requires.txt
agensgraph.egg-info/top_level.txt