Metadata-Version: 1.1
Name: agensgraph
Version: 0.0.2
Summary: A Python driver for Agensgraph
Home-page: https://github.com/iomedhealth/agensgraph
Author: IOMED Medical Solutions SL
Author-email: dev@iomed.es
License: MIT
Keywords: postgres,agensgraph,psycopg2
Platform: UNKNOWN
Classifier: Development Status :: 3 - Alpha
Classifier: Intended Audience :: Developers
Classifier: Topic :: Software Development :: Build Tools
Classifier: License :: OSI Approved :: MIT License
Classifier: Programming Language :: Python :: 3
Classifier: Programming Language :: Python :: 3.4
Classifier: Programming Language :: Python :: 3.5
Classifier: Programming Language :: Python :: 3.6
